COPYING.txt
MANIFEST.in
README.txt
setup.py
sake/__init__.py
sake/app.py
sake/autocompile.py
sake/config.py
sake/const.py
sake/dbghelp.py
sake/errors.py
sake/login.py
sake/loginit.py
sake/logutil.py
sake/loop.py
sake/network.py
sake/pasteServer.py
sake/process.py
sake/session.py
sake/telnetServer.py
sake/traceback2.py
sake/util.py
sake/xreload.py
sake.egg-info/PKG-INFO
sake.egg-info/SOURCES.txt
sake.egg-info/dependency_links.txt
sake.egg-info/requires.txt
sake.egg-info/top_level.txt