Metadata-Version: 1.0
Name: sake
Version: 0.9.0
Summary: Enables easier Stackless Python application development
Home-page: http://code.google.com/p/sake/
Author: Richard Tew
Author-email: richard.m.tew@gmail.com
License: UNKNOWN
Keywords: microthreads,coroutines,stackless,codereloading
Platform: UNKNOWN
Classifier: Programming Language :: Python
Classifier: Programming Language :: Python :: 2
Classifier: Development Status :: 4 - Beta
Classifier: Environment :: Other Environment
Classifier: Intended Audience :: Developers
Classifier: License :: OSI Approved :: MIT License
Classifier: Operating System :: OS Independent
Classifier: Topic :: Software Development :: Libraries :: Python Modules
